[
  {
    "id": "Endpoint-Activity",
    "configuration": {
      "children": [
        {
          "x": 16,
          "y": 0,
          "w": 8,
          "h": 13,
          "i": "3",
          "type": "Widget",
          "widget": {
            "title": "Endpoint Response Time Percentile (ms)"
          },
          "graph": {
            "type": "Line",
            "step": false,
            "smooth": false,
            "showSymbol": false,
            "showXAxis": true,
            "showYAxis": true
          },
          "metrics": [
            "endpoint_percentile"
          ],
          "metricTypes": [
            "readLabeledMetricsValues"
          ],
          "moved": false,
          "metricConfig": [
            {
              "label": "P50, P75, P90, P95, P99",
              "labelsIndex": "0, 1, 2, 3, 4"
            }
          ]
        },
        {
          "x": 8,
          "y": 0,
          "w": 8,
          "h": 13,
          "i": "4",
          "type": "Widget",
          "widget": {
            "title": "Endpoint Avg Response Time (ms)"
          },
          "graph": {
            "type": "Line",
            "step": false,
            "smooth": false,
            "showSymbol": false,
            "showXAxis": true,
            "showYAxis": true
          },
          "metrics": [
            "endpoint_resp_time"
          ],
          "metricTypes": [
            "readMetricsValues"
          ],
          "moved": false
        },
        {
          "x": 0,
          "y": 13,
          "w": 8,
          "h": 13,
          "i": "7",
          "type": "Widget",
          "widget": {
            "title": "Endpoint Success Rate (%)"
          },
          "graph": {
            "type": "Line",
            "step": false,
            "smooth": false,
            "showSymbol": false,
            "showXAxis": true,
            "showYAxis": true
          },
          "metrics": [
            "endpoint_sla"
          ],
          "metricTypes": [
            "readMetricsValues"
          ],
          "moved": false
        },
        {
          "x": 0,
          "y": 0,
          "w": 8,
          "h": 13,
          "i": "8",
          "type": "Widget",
          "widget": {
            "title": "Endpoint Load (calls / min)"
          },
          "graph": {
            "type": "Line",
            "step": false,
            "smooth": false,
            "showSymbol": false,
            "showXAxis": true,
            "showYAxis": true
          },
          "standard": {},
          "metrics": [
            "endpoint_cpm"
          ],
          "metricTypes": [
            "readMetricsValues"
          ],
          "moved": false
        }
      ],
      "layer": "GENERAL",
      "entity": "Endpoint",
      "name": "Endpoint-Activity",
      "isRoot": false
    }
  }
]
